modeling/__init__.py
modeling/build_model.py
modeling/create_layers.py
modeling/optimizer.py
nzp_nmt/modeling/__init__.py
nzp_nmt/modeling/build_model.py
nzp_nmt/modeling/create_layers.py
nzp_nmt/modeling/optimizer.py
nzp_nmt/utils/__init__.py
nzp_nmt/utils/data_load.py
nzp_nmt/utils/hyperparams.py
nzp_nmt/utils/tools.py
nzp_nmt-1.0.3.dist-info/METADATA
nzp_nmt-1.0.3.dist-info/RECORD
nzp_nmt-1.0.3.dist-info/WHEEL
nzp_nmt-1.0.3.dist-info/top_level.txt
utils/__init__.py
utils/data_load.py
utils/hyperparams.py
utils/tools.py
