Metadata-Version: 2.1
Name: nzp-nmt
Version: 1.0.3
Summary: This is my first create!
Home-page: https://github.com/zepen
Author: Niuzepeng
Author-email: 18217127859@163.com
License: MIT
Platform: UNKNOWN
